{
  "task_id": "LCB/abc346_d",
  "passed": true,
  "code": "# YOUR CODE HERE\nimport sys\n\ndef main():\n    import sys\n    input = sys.stdin.read\n    data = input().split()\n    \n    N = int(data[0])\n    S = data[1]\n    C = list(map(int, data[2:]))\n    \n    # We need to find the minimum cost to make S a good string.\n    # A good string has exactly one pair of consecutive identical characters.\n    \n    # We will consider all possible positions where the duplicate pair can occur.\n    # For each possible position i (1 <= i <= N-1), we will compute the cost to make S have exactly one duplicate pair at i.\n    \n    # We will try all possible positions for the duplicate pair and compute the minimum cost.\n    \n    min_cost = float('inf')\n    \n    # Try each possible position for the duplicate pair\n    for i in range(N - 1):\n        # We want S[i] == S[i+1]\n        # So we can either flip S[i] or S[i+1] to match the other, or leave them as is.\n        # We will compute the cost to make S[i] == S[i+1], and ensure that all other consecutive pairs are different.\n        \n        # We will create a new string T that is a copy of S, and for each position, we will decide whether to flip it.\n        # We will compute the cost to make S[i] == S[i+1], and ensure that all other consecutive pairs are different.\n        \n        # We will compute the cost to make S[i] == S[i+1], and ensure that all other consecutive pairs are different.\n        # We will compute the cost for this configuration.\n        \n        cost = 0\n        # We will create a list of flips (0 or 1) to apply to S to make it a good string.\n        flips = [0] * N\n        \n        # First, make S[i] == S[i+1]\n        if S[i] != S[i+1]:\n            # We need to flip one of them\n            # We can choose to flip S[i] or S[i+1], whichever has lower cost\n            if C[i] < C[i+1]:\n                flips[i] = 1\n                cost += C[i]\n            else:\n                flips[i+1] = 1\n                cost += C[i+1]\n        \n        # Now, ensure that all other consecutive pairs are different\n        for j in range(N - 1):\n            if j == i:\n                continue\n            # We want S[j] != S[j+1]\n            # So we need to check if they are already different, or if we need to flip one of them.\n            # We will check the current state of S[j] and S[j+1] after applying flips\n            current_j = S[j] if flips[j] == 0 else ('1' if S[j] == '0' else '0')\n            current_j1 = S[j+1] if flips[j+1] == 0 else ('1' if S[j+1] == '0' else '0')\n            \n            if current_j == current_j1:\n                # They are the same, need to flip one of them\n                # Choose the one with lower cost\n                if C[j] < C[j+1]:\n                    flips[j] = 1 - flips[j]\n                    cost += C[j]\n                else:\n                    flips[j+1] = 1 - flips[j+1]\n                    cost += C[j+1]\n        \n        # Update the minimum cost\n        min_cost = min(min_cost, cost)\n    \n    print(min_cost)\n\nif __name__ == \"__main__\":\n    main()",
  "phase_solved": "phase1",
  "candidates_generated": 8,
  "total_tokens": 10402,
  "total_time_ms": 648427.344083786,
  "telemetry": {
    "adaptive_k": 8,
    "budget_tier": "extreme",
    "plansearch_tokens": 9875
  }
}