{
  "task_id": "LCB/abc341_e",
  "passed": true,
  "code": "import sys\nimport threading\n\ndef main():\n    import sys\n    input = sys.stdin.read\n    data = input().split()\n    idx = 0\n    N = int(data[idx])\n    idx += 1\n    Q = int(data[idx])\n    idx += 1\n    S = data[idx]\n    idx += 1\n\n    # Segment tree for range flip and range query\n    class SegmentTree:\n        def __init__(self, data):\n            self.n = len(data)\n            self.tree = [0] * (4 * self.n)\n            self.lazy = [0] * (4 * self.n)\n            self.build(0, 0, self.n - 1, data)\n\n        def build(self, node, l, r, data):\n            if l == r:\n                self.tree[node] = int(data[l])\n                return\n            mid = (l + r) // 2\n            self.build(2 * node + 1, l, mid, data)\n            self.build(2 * node + 2, mid + 1, r, data)\n            self.tree[node] = self.tree[2 * node + 1] + self.tree[2 * node + 2]\n\n        def push(self, node, l, r):\n            if self.lazy[node] != 0:\n                mid = (l + r) // 2\n                left = 2 * node + 1\n                right = 2 * node + 2\n                self.tree[left] = (mid - l + 1) - self.tree[left]\n                self.lazy[left] ^= 1\n                self.tree[right] = (r - mid) - self.tree[right]\n                self.lazy[right] ^= 1\n                self.lazy[node] = 0\n\n        def update_range(self, node, l, r, ul, ur):\n            if ur < l or ul > r:\n                return\n            if ul <= l and r <= ur:\n                self.tree[node] = (r - l + 1) - self.tree[node]\n                self.lazy[node] ^= 1\n                return\n            self.push(node, l, r)\n            mid = (l + r) // 2\n            self.update_range(2 * node + 1, l, mid, ul, ur)\n            self.update_range(2 * node + 2, mid + 1, r, ul, ur)\n            self.tree[node] = self.tree[2 * node + 1] + self.tree[2 * node + 2]\n\n        def query(self, node, l, r, ql, qr):\n            if qr < l or ql > r:\n                return 0\n            if ql <= l and r <= qr:\n                return self.tree[node]\n            self.push(node, l, r)\n            mid = (l + r) // 2\n            left_sum = self.query(2 * node + 1, l, mid, ql, qr)\n            right_sum = self.query(2 * node + 2, mid + 1, r, ql, qr)\n            return left_sum + right_sum\n\n    st = SegmentTree(S)\n\n    res = []\n\n    for _ in range(Q):\n        t = int(data[idx])\n        idx += 1\n        L = int(data[idx])\n        idx += 1\n        R = int(data[idx])\n        idx += 1\n        if t == 1:\n            st.update_range(0, 0, N - 1, L - 1, R - 1)\n        else:\n            # Check if the substring is good\n            # A good string has no two consecutive same characters\n            # So, for the range [L-1, R-1], the number of transitions (0 to 1 or 1 to 0) should be (R - L + 1) - 1\n            # Because a good string of length m has m-1 transitions\n            length = R - L + 1\n            if length == 1:\n                res.append(\"Yes\")\n                continue\n            total = st.query(0, 0, N - 1, L - 1, R - 1)\n            # The number of transitions is (total + 1) if the first character is 1, or (length - total) if the first character is 0\n            # But we can't directly get the first character, so we need to check the first and last character\n            first = st.query(0, 0, N - 1, L - 1, L - 1)\n            last = st.query(0, 0, N - 1, R - 1, R - 1)\n            if first == last:\n                # If first and last are same, then the number of transitions is (length - 1) - (total - (first + last) // 2)\n                # But this is complicated. Instead, we can check if the number of 1s is equal to the number of 0s or differs by 1\n                # For a good string, the number of 1s and 0s can differ by at most 1\n                # And the number of transitions is (length - 1)\n                # So, if the number of 1s is not equal to the number of 0s or differs by 1, it's not a good string\n                if abs(total - (length - total)) > 1:\n                    res.append(\"No\")\n                else:\n                    res.append(\"Yes\")\n            else:\n                if abs(total - (length - total)) > 0:\n                    res.append(\"No\")\n                else:\n                    res.append(\"Yes\")\n\n    print(\"\\n\".join(res))\n\nthreading.Thread(target=main).start()",
  "phase_solved": "phase1",
  "candidates_generated": 5,
  "total_tokens": 10799,
  "total_time_ms": 180910.09044647217,
  "telemetry": {
    "adaptive_k": 5,
    "budget_tier": "hard",
    "plansearch_tokens": 9570
  }
}